{"table18": {"fileUrl": "http://ot2gqnlv6.bkt.clouddn.com/dressplus/goods/table18.jpg", "detectData": []}, "table19": {"fileUrl": "http://ot2gqnlv6.bkt.clouddn.com/dressplus/goods/table19.jpg", "detectData": [{"object_confidence": 75, "object_name": "\u67dc\u5b50", "object_bounding_box": {"y": 0.1675, "width": 0.3927272727272727, "height": 0.605, "x": 0.4818181818181818}}, {"object_confidence": 77, "object_name": "\u684c\u5b50", "object_bounding_box": {"y": 0.5275, "width": 0.4490909090909091, "height": 0.4175, "x": 0.24}}]}, "table10": {"fileUrl": "http://ot2gqnlv6.bkt.clouddn.com/dressplus/goods/table10.jpg", "detectData": [{"object_confidence": 94, "object_name": "\u684c\u5b50", "object_bounding_box": {"y": 0.5864197530864198, "width": 0.4722222222222222, "height": 0.404320987654321, "x": 0.35648148148148145}}]}, "table11": {"fileUrl": "http://ot2gqnlv6.bkt.clouddn.com/dressplus/goods/table11.jpg", "detectData": [{"object_confidence": 99, "object_name": "\u684c\u5b50", "object_bounding_box": {"y": 0.6111111111111112, "width": 0.3, "height": 0.2822222222222222, "x": 0.132}}, {"object_confidence": 85, "object_name": "\u684c\u5b50", "object_bounding_box": {"y": 0.6555555555555556, "width": 0.31, "height": 0.32222222222222224, "x": 0.688}}]}, "table12": {"fileUrl": "http://ot2gqnlv6.bkt.clouddn.com/dressplus/goods/table12.jpg", "detectData": []}, "table13": {"fileUrl": "http://ot2gqnlv6.bkt.clouddn.com/dressplus/goods/table13.jpg", "detectData": [{"object_confidence": 73, "object_name": "\u67dc\u5b50", "object_bounding_box": {"y": 0.52, "width": 0.245, "height": 0.3025, "x": 0.02}}, {"object_confidence": 91, "object_name": "\u684c\u5b50", "object_bounding_box": {"y": 0.52, "width": 0.30666666666666664, "height": 0.375, "x": 0.25666666666666665}}]}, "table14": {"fileUrl": "http://ot2gqnlv6.bkt.clouddn.com/dressplus/goods/table14.jpg", "detectData": [{"object_confidence": 95, "object_name": "\u684c\u5b50", "object_bounding_box": {"y": 0.6083333333333333, "width": 0.3283333333333333, "height": 0.3527777777777778, "x": 0.06}}, {"object_confidence": 85, "object_name": "\u684c\u5b50", "object_bounding_box": {"y": 0.5472222222222223, "width": 0.265, "height": 0.4, "x": 0.45666666666666667}}]}, "table15": {"fileUrl": "http://ot2gqnlv6.bkt.clouddn.com/dressplus/goods/table15.jpg", "detectData": [{"object_confidence": 91, "object_name": "\u684c\u5b50", "object_bounding_box": {"y": 0.52, "width": 0.6016666666666667, "height": 0.4675, "x": 0.21333333333333335}}]}, "table16": {"fileUrl": "http://ot2gqnlv6.bkt.clouddn.com/dressplus/goods/table16.jpg", "detectData": [{"object_confidence": 98, "object_name": "\u684c\u5b50", "object_bounding_box": {"y": 0.5786666666666667, "width": 0.488, "height": 0.4186666666666667, "x": 0.394}}]}, "table17": {"fileUrl": "http://ot2gqnlv6.bkt.clouddn.com/dressplus/goods/table17.jpg", "detectData": [{"object_confidence": 95, "object_name": "\u684c\u5b50", "object_bounding_box": {"y": 0.6196078431372549, "width": 0.6890625, "height": 0.36470588235294116, "x": 0.165625}}]}, "table2": {"fileUrl": "http://ot2gqnlv6.bkt.clouddn.com/dressplus/goods/table2.jpg", "detectData": [{"object_confidence": 87, "object_name": "\u684c\u5b50", "object_bounding_box": {"y": 0.6361111111111111, "width": 0.415625, "height": 0.35555555555555557, "x": 0.3625}}]}, "table3": {"fileUrl": "http://ot2gqnlv6.bkt.clouddn.com/dressplus/goods/table3.jpg", "detectData": [{"object_confidence": 97, "object_name": "\u684c\u5b50", "object_bounding_box": {"y": 0.5640326975476839, "width": 0.5381818181818182, "height": 0.4332425068119891, "x": 0.31636363636363635}}]}, "table1": {"fileUrl": "http://ot2gqnlv6.bkt.clouddn.com/dressplus/goods/table1.jpg", "detectData": [{"object_confidence": 99, "object_name": "\u684c\u5b50", "object_bounding_box": {"y": 0.5080459770114942, "width": 0.33166666666666667, "height": 0.4666666666666667, "x": 0.30666666666666664}}]}, "table6": {"fileUrl": "http://ot2gqnlv6.bkt.clouddn.com/dressplus/goods/table6.jpg", "detectData": [{"object_confidence": 97, "object_name": "\u684c\u5b50", "object_bounding_box": {"y": 0.5240963855421686, "width": 0.474, "height": 0.4006024096385542, "x": 0.188}}]}, "table7": {"fileUrl": "http://ot2gqnlv6.bkt.clouddn.com/dressplus/goods/table7.jpg", "detectData": [{"object_confidence": 95, "object_name": "\u684c\u5b50", "object_bounding_box": {"y": 0.5031315240083507, "width": 0.3015625, "height": 0.3736951983298539, "x": 0.290625}}]}, "table4": {"fileUrl": "http://ot2gqnlv6.bkt.clouddn.com/dressplus/goods/table4.jpg", "detectData": [{"object_confidence": 96, "object_name": "\u684c\u5b50", "object_bounding_box": {"y": 0.5175, "width": 0.4, "height": 0.405, "x": 0.218}}]}, "table5": {"fileUrl": "http://ot2gqnlv6.bkt.clouddn.com/dressplus/goods/table5.jpg", "detectData": [{"object_confidence": 94, "object_name": "\u684c\u5b50", "object_bounding_box": {"y": 0.328804347826087, "width": 0.706, "height": 0.6195652173913043, "x": 0.272}}]}, "table8": {"fileUrl": "http://ot2gqnlv6.bkt.clouddn.com/dressplus/goods/table8.jpg", "detectData": [{"object_confidence": 98, "object_name": "\u684c\u5b50", "object_bounding_box": {"y": 0.5670498084291188, "width": 0.37333333333333335, "height": 0.39846743295019155, "x": 0.18333333333333332}}]}, "table9": {"fileUrl": "http://ot2gqnlv6.bkt.clouddn.com/dressplus/goods/table9.jpg", "detectData": [{"object_confidence": 99, "object_name": "\u684c\u5b50", "object_bounding_box": {"y": 0.5783333333333334, "width": 0.42333333333333334, "height": 0.37833333333333335, "x": 0.30833333333333335}}]}, "table83": {"fileUrl": "http://ot2gqnlv6.bkt.clouddn.com/dressplus/goods/table83.jpg", "detectData": [{"object_confidence": 90, "object_name": "\u684c\u5b50", "object_bounding_box": {"y": 0.4924965893587995, "width": 0.42818181818181816, "height": 0.43383356070941337, "x": 0.56}}, {"object_confidence": 76, "object_name": "\u684c\u5b50", "object_bounding_box": {"y": 0.6193724420190996, "width": 0.3654545454545455, "height": 0.3656207366984993, "x": 0.2909090909090909}}]}, "table82": {"fileUrl": "http://ot2gqnlv6.bkt.clouddn.com/dressplus/goods/table82.jpg", "detectData": [{"object_confidence": 96, "object_name": "\u684c\u5b50", "object_bounding_box": {"y": 0.5469208211143695, "width": 0.404296875, "height": 0.4398826979472141, "x": 0.2353515625}}]}, "table81": {"fileUrl": "http://ot2gqnlv6.bkt.clouddn.com/dressplus/goods/table81.jpg", "detectData": [{"object_confidence": 93, "object_name": "\u684c\u5b50", "object_bounding_box": {"y": 0.6213740458015267, "width": 0.4536363636363636, "height": 0.35725190839694654, "x": 0.27090909090909093}}]}, "table80": {"fileUrl": "http://ot2gqnlv6.bkt.clouddn.com/dressplus/goods/table80.jpg", "detectData": []}, "table87": {"fileUrl": "http://ot2gqnlv6.bkt.clouddn.com/dressplus/goods/table87.jpg", "detectData": []}, "table86": {"fileUrl": "http://ot2gqnlv6.bkt.clouddn.com/dressplus/goods/table86.jpg", "detectData": [{"object_confidence": 89, "object_name": "\u67dc\u5b50", "object_bounding_box": {"y": 0.022535211267605635, "width": 0.1890909090909091, "height": 0.8394366197183099, "x": 0}}, {"object_confidence": 96, "object_name": "\u684c\u5b50", "object_bounding_box": {"y": 0.5464788732394367, "width": 0.37454545454545457, "height": 0.3464788732394366, "x": 0.3381818181818182}}]}, "table85": {"fileUrl": "http://ot2gqnlv6.bkt.clouddn.com/dressplus/goods/table85.jpg", "detectData": [{"object_confidence": 95, "object_name": "\u684c\u5b50", "object_bounding_box": {"y": 0.5422343324250681, "width": 0.30727272727272725, "height": 0.3787465940054496, "x": 0.30636363636363634}}]}, "table84": {"fileUrl": "http://ot2gqnlv6.bkt.clouddn.com/dressplus/goods/table84.jpg", "detectData": [{"object_confidence": 94, "object_name": "\u684c\u5b50", "object_bounding_box": {"y": 0.5183333333333333, "width": 0.4683684794672586, "height": 0.4483333333333333, "x": 0.19866814650388456}}]}, "table89": {"fileUrl": "http://ot2gqnlv6.bkt.clouddn.com/dressplus/goods/table89.jpg", "detectData": [{"object_confidence": 95, "object_name": "\u684c\u5b50", "object_bounding_box": {"y": 0.55, "width": 0.3188888888888889, "height": 0.3616666666666667, "x": 0.2288888888888889}}]}, "table88": {"fileUrl": "http://ot2gqnlv6.bkt.clouddn.com/dressplus/goods/table88.jpg", "detectData": []}, "table25": {"fileUrl": "http://ot2gqnlv6.bkt.clouddn.com/dressplus/goods/table25.jpg", "detectData": [{"object_confidence": 78, "object_name": "\u67dc\u5b50", "object_bounding_box": {"y": 0.458980044345898, "width": 0.20208604954367665, "height": 0.3237250554323725, "x": 0.7685788787483703}}, {"object_confidence": 97, "object_name": "\u684c\u5b50", "object_bounding_box": {"y": 0.5454545454545454, "width": 0.5358539765319427, "height": 0.45121951219512196, "x": 0.19882659713168188}}]}, "table24": {"fileUrl": "http://ot2gqnlv6.bkt.clouddn.com/dressplus/goods/table24.jpg", "detectData": [{"object_confidence": 84, "object_name": "\u684c\u5b50", "object_bounding_box": {"y": 0.6238030095759234, "width": 0.2119140625, "height": 0.26812585499316005, "x": 0.49609375}}]}, "table27": {"fileUrl": "http://ot2gqnlv6.bkt.clouddn.com/dressplus/goods/table27.jpg", "detectData": [{"object_confidence": 89, "object_name": "\u684c\u5b50", "object_bounding_box": {"y": 0.5293427230046949, "width": 0.5153695225637671, "height": 0.43896713615023475, "x": 0.275997383911053}}]}, "table26": {"fileUrl": "http://ot2gqnlv6.bkt.clouddn.com/dressplus/goods/table26.jpg", "detectData": [{"object_confidence": 78, "object_name": "\u5e8a\u4f53", "object_bounding_box": {"y": 0.48924122310305773, "width": 0.32702349869451697, "height": 0.3012457531143828, "x": 0.664490861618799}}, {"object_confidence": 91, "object_name": "\u684c\u5b50", "object_bounding_box": {"y": 0.5583238958097395, "width": 0.24281984334203655, "height": 0.4031710079275198, "x": 0.4073107049608355}}]}, "table21": {"fileUrl": "http://ot2gqnlv6.bkt.clouddn.com/dressplus/goods/table21.jpg", "detectData": [{"object_confidence": 98, "object_name": "\u684c\u5b50", "object_bounding_box": {"y": 0.5383333333333333, "width": 0.45625, "height": 0.43416666666666665, "x": 0.465625}}]}, "table20": {"fileUrl": "http://ot2gqnlv6.bkt.clouddn.com/dressplus/goods/table20.jpg", "detectData": []}, "table23": {"fileUrl": "http://ot2gqnlv6.bkt.clouddn.com/dressplus/goods/table23.jpg", "detectData": []}, "table22": {"fileUrl": "http://ot2gqnlv6.bkt.clouddn.com/dressplus/goods/table22.jpg", "detectData": [{"object_confidence": 99, "object_name": "\u684c\u5b50", "object_bounding_box": {"y": 0.5304054054054054, "width": 0.35584415584415585, "height": 0.39864864864864863, "x": 0.33766233766233766}}]}, "table29": {"fileUrl": "http://ot2gqnlv6.bkt.clouddn.com/dressplus/goods/table29.jpg", "detectData": [{"object_confidence": 94, "object_name": "\u684c\u5b50", "object_bounding_box": {"y": 0.4571092831962397, "width": 0.4407334643091028, "height": 0.48531139835487663, "x": 0.2704649639816634}}]}, "table28": {"fileUrl": "http://ot2gqnlv6.bkt.clouddn.com/dressplus/goods/table28.jpg", "detectData": [{"object_confidence": 86, "object_name": "\u684c\u5b50", "object_bounding_box": {"y": 0.6093567251461989, "width": 0.36411263916175507, "height": 0.3707602339181287, "x": 0.5710543549443353}}]}, "table90": {"fileUrl": "http://ot2gqnlv6.bkt.clouddn.com/dressplus/goods/table90.jpg", "detectData": [{"object_confidence": 98, "object_name": "\u684c\u5b50", "object_bounding_box": {"y": 0.5245231607629428, "width": 0.4509090909090909, "height": 0.4318801089918256, "x": 0.15363636363636363}}]}, "table91": {"fileUrl": "http://ot2gqnlv6.bkt.clouddn.com/dressplus/goods/table91.jpg", "detectData": []}, "table92": {"fileUrl": "http://ot2gqnlv6.bkt.clouddn.com/dressplus/goods/table92.jpg", "detectData": [{"object_confidence": 99, "object_name": "\u684c\u5b50", "object_bounding_box": {"y": 0.5836363636363636, "width": 0.47385272145144075, "height": 0.35818181818181816, "x": 0.2710779082177161}}]}, "table93": {"fileUrl": "http://ot2gqnlv6.bkt.clouddn.com/dressplus/goods/table93.jpg", "detectData": []}, "table94": {"fileUrl": "http://ot2gqnlv6.bkt.clouddn.com/dressplus/goods/table94.jpg", "detectData": [{"object_confidence": 98, "object_name": "\u684c\u5b50", "object_bounding_box": {"y": 0.5083333333333333, "width": 0.49, "height": 0.49, "x": 0.31222222222222223}}]}, "table95": {"fileUrl": "http://ot2gqnlv6.bkt.clouddn.com/dressplus/goods/table95.jpg", "detectData": [{"object_confidence": 73, "object_name": "\u67dc\u5b50", "object_bounding_box": {"y": 0.03666666666666667, "width": 0.24555555555555555, "height": 0.5516666666666666, "x": 0}}, {"object_confidence": 98, "object_name": "\u684c\u5b50", "object_bounding_box": {"y": 0.5866666666666667, "width": 0.39444444444444443, "height": 0.4116666666666667, "x": 0.30666666666666664}}]}, "table96": {"fileUrl": "http://ot2gqnlv6.bkt.clouddn.com/dressplus/goods/table96.jpg", "detectData": [{"object_confidence": 98, "object_name": "\u684c\u5b50", "object_bounding_box": {"y": 0.6042296072507553, "width": 0.2918181818181818, "height": 0.3564954682779456, "x": 0.3281818181818182}}]}, "table97": {"fileUrl": "http://ot2gqnlv6.bkt.clouddn.com/dressplus/goods/table97.jpg", "detectData": [{"object_confidence": 93, "object_name": "\u684c\u5b50", "object_bounding_box": {"y": 0.41363636363636364, "width": 0.5454545454545454, "height": 0.5787878787878787, "x": 0.22828282828282828}}]}, "table98": {"fileUrl": "http://ot2gqnlv6.bkt.clouddn.com/dressplus/goods/table98.jpg", "detectData": []}, "table99": {"fileUrl": "http://ot2gqnlv6.bkt.clouddn.com/dressplus/goods/table99.jpg", "detectData": [{"object_confidence": 98, "object_name": "\u684c\u5b50", "object_bounding_box": {"y": 0.5852660300136425, "width": 0.3654545454545455, "height": 0.3956343792633015, "x": 0.3418181818181818}}]}, "table32": {"fileUrl": "http://ot2gqnlv6.bkt.clouddn.com/dressplus/goods/table32.jpg", "detectData": [{"object_confidence": 89, "object_name": "\u684c\u5b50", "object_bounding_box": {"y": 0.5963938973647711, "width": 0.43474264705882354, "height": 0.36615811373092927, "x": 0.22886029411764705}}]}, "table33": {"fileUrl": "http://ot2gqnlv6.bkt.clouddn.com/dressplus/goods/table33.jpg", "detectData": []}, "table30": {"fileUrl": "http://ot2gqnlv6.bkt.clouddn.com/dressplus/goods/table30.jpg", "detectData": [{"object_confidence": 86, "object_name": "\u67dc\u5b50", "object_bounding_box": {"y": 0.3117178612059158, "width": 0.31699346405228757, "height": 0.6382252559726962, "x": 0.6601307189542484}}, {"object_confidence": 85, "object_name": "\u684c\u5b50", "object_bounding_box": {"y": 0.6188850967007964, "width": 0.40980392156862744, "height": 0.31968145620022753, "x": 0.14575163398692811}}, {"object_confidence": 77, "object_name": "\u684c\u5b50", "object_bounding_box": {"y": 0.29579067121729236, "width": 0.26862745098039215, "height": 0.5574516496018203, "x": 0.550326797385621}}]}, "table31": {"fileUrl": "http://ot2gqnlv6.bkt.clouddn.com/dressplus/goods/table31.jpg", "detectData": [{"object_confidence": 99, "object_name": "\u684c\u5b50", "object_bounding_box": {"y": 0.5341830822711472, "width": 0.5418060200668896, "height": 0.354577056778679, "x": 0.22240802675585283}}]}, "table36": {"fileUrl": "http://ot2gqnlv6.bkt.clouddn.com/dressplus/goods/table36.jpg", "detectData": [{"object_confidence": 94, "object_name": "\u684c\u5b50", "object_bounding_box": {"y": 0.576797385620915, "width": 0.2973856209150327, "height": 0.37254901960784315, "x": 0.30501089324618735}}]}, "table37": {"fileUrl": "http://ot2gqnlv6.bkt.clouddn.com/dressplus/goods/table37.jpg", "detectData": [{"object_confidence": 76, "object_name": "\u684c\u5b50", "object_bounding_box": {"y": 0.5806938159879337, "width": 0.3427272727272727, "height": 0.39668174962292607, "x": 0.3009090909090909}}]}, "table34": {"fileUrl": "http://ot2gqnlv6.bkt.clouddn.com/dressplus/goods/table34.jpg", "detectData": [{"object_confidence": 99, "object_name": "\u684c\u5b50", "object_bounding_box": {"y": 0.6027272727272728, "width": 0.5598455598455598, "height": 0.3927272727272727, "x": 0.16891891891891891}}]}, "table35": {"fileUrl": "http://ot2gqnlv6.bkt.clouddn.com/dressplus/goods/table35.jpg", "detectData": [{"object_confidence": 99, "object_name": "\u684c\u5b50", "object_bounding_box": {"y": 0.5558823529411765, "width": 0.44847890088321885, "height": 0.4176470588235294, "x": 0.47791952894995093}}]}, "table38": {"fileUrl": "http://ot2gqnlv6.bkt.clouddn.com/dressplus/goods/table38.jpg", "detectData": []}, "table39": {"fileUrl": "http://ot2gqnlv6.bkt.clouddn.com/dressplus/goods/table39.jpg", "detectData": []}, "table100": {"fileUrl": "http://ot2gqnlv6.bkt.clouddn.com/dressplus/goods/table100.jpg", "detectData": []}, "table47": {"fileUrl": "http://ot2gqnlv6.bkt.clouddn.com/dressplus/goods/table47.jpg", "detectData": []}, "table46": {"fileUrl": "http://ot2gqnlv6.bkt.clouddn.com/dressplus/goods/table46.jpg", "detectData": []}, "table45": {"fileUrl": "http://ot2gqnlv6.bkt.clouddn.com/dressplus/goods/table45.jpg", "detectData": []}, "table44": {"fileUrl": "http://ot2gqnlv6.bkt.clouddn.com/dressplus/goods/table44.jpg", "detectData": [{"object_confidence": 70, "object_name": "\u67dc\u5b50", "object_bounding_box": {"y": 0.09826589595375723, "width": 0.20454545454545456, "height": 0.7528901734104047, "x": 0.6890909090909091}}, {"object_confidence": 97, "object_name": "\u684c\u5b50", "object_bounding_box": {"y": 0.5375722543352601, "width": 0.48454545454545456, "height": 0.45375722543352603, "x": 0.15}}]}, "table43": {"fileUrl": "http://ot2gqnlv6.bkt.clouddn.com/dressplus/goods/table43.jpg", "detectData": [{"object_confidence": 97, "object_name": "\u684c\u5b50", "object_bounding_box": {"y": 0.43169398907103823, "width": 0.5227272727272727, "height": 0.4849726775956284, "x": 0.28}}]}, "table42": {"fileUrl": "http://ot2gqnlv6.bkt.clouddn.com/dressplus/goods/table42.jpg", "detectData": [{"object_confidence": 98, "object_name": "\u684c\u5b50", "object_bounding_box": {"y": 0.5866302864938608, "width": 0.5127272727272727, "height": 0.3806275579809004, "x": 0.13272727272727272}}]}, "table41": {"fileUrl": "http://ot2gqnlv6.bkt.clouddn.com/dressplus/goods/table41.jpg", "detectData": [{"object_confidence": 97, "object_name": "\u684c\u5b50", "object_bounding_box": {"y": 0.5306957708049114, "width": 0.24272727272727274, "height": 0.3710777626193724, "x": 0.4218181818181818}}]}, "table40": {"fileUrl": "http://ot2gqnlv6.bkt.clouddn.com/dressplus/goods/table40.jpg", "detectData": []}, "table49": {"fileUrl": "http://ot2gqnlv6.bkt.clouddn.com/dressplus/goods/table49.jpg", "detectData": [{"object_confidence": 96, "object_name": "\u684c\u5b50", "object_bounding_box": {"y": 0.5402455661664393, "width": 0.2736363636363636, "height": 0.3942701227830832, "x": 0.38272727272727275}}]}, "table48": {"fileUrl": "http://ot2gqnlv6.bkt.clouddn.com/dressplus/goods/table48.jpg", "detectData": []}, "table54": {"fileUrl": "http://ot2gqnlv6.bkt.clouddn.com/dressplus/goods/table54.jpg", "detectData": [{"object_confidence": 98, "object_name": "\u684c\u5b50", "object_bounding_box": {"y": 0.5846599131693199, "width": 0.3409090909090909, "height": 0.4081041968162084, "x": 0.17181818181818181}}]}, "table55": {"fileUrl": "http://ot2gqnlv6.bkt.clouddn.com/dressplus/goods/table55.jpg", "detectData": [{"object_confidence": 99, "object_name": "\u684c\u5b50", "object_bounding_box": {"y": 0.538881309686221, "width": 0.49272727272727274, "height": 0.451568894952251, "x": 0.30363636363636365}}]}, "table56": {"fileUrl": "http://ot2gqnlv6.bkt.clouddn.com/dressplus/goods/table56.jpg", "detectData": [{"object_confidence": 97, "object_name": "\u684c\u5b50", "object_bounding_box": {"y": 0.4829467939972715, "width": 0.28, "height": 0.3860845839017735, "x": 0.2190909090909091}}]}, "table57": {"fileUrl": "http://ot2gqnlv6.bkt.clouddn.com/dressplus/goods/table57.jpg", "detectData": [{"object_confidence": 93, "object_name": "\u67dc\u5b50", "object_bounding_box": {"y": 0, "width": 0.27545454545454545, "height": 0.8933764135702746, "x": 0}}, {"object_confidence": 96, "object_name": "\u684c\u5b50", "object_bounding_box": {"y": 0.5638126009693053, "width": 0.2545454545454545, "height": 0.3764135702746365, "x": 0.36727272727272725}}]}, "table50": {"fileUrl": "http://ot2gqnlv6.bkt.clouddn.com/dressplus/goods/table50.jpg", "detectData": [{"object_confidence": 96, "object_name": "\u684c\u5b50", "object_bounding_box": {"y": 0.495225102319236, "width": 0.6372727272727273, "height": 0.5034106412005457, "x": 0.2672727272727273}}, {"object_confidence": 74, "object_name": "\u684c\u5b50", "object_bounding_box": {"y": 0.3792633015006821, "width": 0.23454545454545456, "height": 0.37789904502046384, "x": 0.0027272727272727275}}]}, "table51": {"fileUrl": "http://ot2gqnlv6.bkt.clouddn.com/dressplus/goods/table51.jpg", "detectData": [{"object_confidence": 99, "object_name": "\u684c\u5b50", "object_bounding_box": {"y": 0.49696969696969695, "width": 0.40404040404040403, "height": 0.43636363636363634, "x": 0.35555555555555557}}]}, "table52": {"fileUrl": "http://ot2gqnlv6.bkt.clouddn.com/dressplus/goods/table52.jpg", "detectData": []}, "table53": {"fileUrl": "http://ot2gqnlv6.bkt.clouddn.com/dressplus/goods/table53.jpg", "detectData": []}, "table58": {"fileUrl": "http://ot2gqnlv6.bkt.clouddn.com/dressplus/goods/table58.jpg", "detectData": []}, "table59": {"fileUrl": "http://ot2gqnlv6.bkt.clouddn.com/dressplus/goods/table59.jpg", "detectData": []}, "table61": {"fileUrl": "http://ot2gqnlv6.bkt.clouddn.com/dressplus/goods/table61.jpg", "detectData": [{"object_confidence": 72, "object_name": "\u67dc\u5b50", "object_bounding_box": {"y": 0.0704647676161919, "width": 0.501, "height": 0.6926536731634183, "x": 0.039}}, {"object_confidence": 92, "object_name": "\u684c\u5b50", "object_bounding_box": {"y": 0.5217391304347826, "width": 0.406, "height": 0.42278860569715143, "x": 0.243}}]}, "table60": {"fileUrl": "http://ot2gqnlv6.bkt.clouddn.com/dressplus/goods/table60.jpg", "detectData": [{"object_confidence": 96, "object_name": "\u684c\u5b50", "object_bounding_box": {"y": 0.5605442176870749, "width": 0.4127272727272727, "height": 0.39727891156462586, "x": 0.2881818181818182}}]}, "table63": {"fileUrl": "http://ot2gqnlv6.bkt.clouddn.com/dressplus/goods/table63.jpg", "detectData": [{"object_confidence": 75, "object_name": "\u67dc\u5b50", "object_bounding_box": {"y": 0.14343163538873996, "width": 0.4490909090909091, "height": 0.6943699731903485, "x": 0.17545454545454545}}, {"object_confidence": 97, "object_name": "\u684c\u5b50", "object_bounding_box": {"y": 0.6273458445040214, "width": 0.3809090909090909, "height": 0.3646112600536193, "x": 0.32545454545454544}}]}, "table62": {"fileUrl": "http://ot2gqnlv6.bkt.clouddn.com/dressplus/goods/table62.jpg", "detectData": [{"object_confidence": 95, "object_name": "\u684c\u5b50", "object_bounding_box": {"y": 0.514324693042292, "width": 0.4763636363636364, "height": 0.36971350613915416, "x": 0.11545454545454545}}, {"object_confidence": 74, "object_name": "\u684c\u5b50", "object_bounding_box": {"y": 0.5811732605729877, "width": 0.25727272727272726, "height": 0.2783083219645293, "x": 0.6263636363636363}}]}, "table65": {"fileUrl": "http://ot2gqnlv6.bkt.clouddn.com/dressplus/goods/table65.jpg", "detectData": []}, "table64": {"fileUrl": "http://ot2gqnlv6.bkt.clouddn.com/dressplus/goods/table64.jpg", "detectData": [{"object_confidence": 97, "object_name": "\u684c\u5b50", "object_bounding_box": {"y": 0.522633744855967, "width": 0.36363636363636365, "height": 0.4348422496570645, "x": 0.2381818181818182}}]}, "table67": {"fileUrl": "http://ot2gqnlv6.bkt.clouddn.com/dressplus/goods/table67.jpg", "detectData": [{"object_confidence": 88, "object_name": "\u684c\u5b50", "object_bounding_box": {"y": 0.660300136425648, "width": 0.3490909090909091, "height": 0.3383356070941337, "x": 0.3145454545454546}}]}, "table66": {"fileUrl": "http://ot2gqnlv6.bkt.clouddn.com/dressplus/goods/table66.jpg", "detectData": [{"object_confidence": 99, "object_name": "\u684c\u5b50", "object_bounding_box": {"y": 0.5818181818181818, "width": 0.5470668485675307, "height": 0.37272727272727274, "x": 0.19236016371077763}}]}, "table69": {"fileUrl": "http://ot2gqnlv6.bkt.clouddn.com/dressplus/goods/table69.jpg", "detectData": [{"object_confidence": 97, "object_name": "\u684c\u5b50", "object_bounding_box": {"y": 0.6335877862595419, "width": 0.27545454545454545, "height": 0.34961832061068704, "x": 0.3790909090909091}}]}, "table68": {"fileUrl": "http://ot2gqnlv6.bkt.clouddn.com/dressplus/goods/table68.jpg", "detectData": [{"object_confidence": 87, "object_name": "\u684c\u5b50", "object_bounding_box": {"y": 0.4763271162123386, "width": 0.39, "height": 0.4017216642754663, "x": 0.295}}]}, "table78": {"fileUrl": "http://ot2gqnlv6.bkt.clouddn.com/dressplus/goods/table78.jpg", "detectData": [{"object_confidence": 94, "object_name": "\u684c\u5b50", "object_bounding_box": {"y": 0.6091603053435114, "width": 0.44545454545454544, "height": 0.36793893129770994, "x": 0.22363636363636363}}]}, "table79": {"fileUrl": "http://ot2gqnlv6.bkt.clouddn.com/dressplus/goods/table79.jpg", "detectData": []}, "table76": {"fileUrl": "http://ot2gqnlv6.bkt.clouddn.com/dressplus/goods/table76.jpg", "detectData": [{"object_confidence": 98, "object_name": "\u684c\u5b50", "object_bounding_box": {"y": 0.5634379263301501, "width": 0.35363636363636364, "height": 0.38472032742155526, "x": 0.2690909090909091}}]}, "table77": {"fileUrl": "http://ot2gqnlv6.bkt.clouddn.com/dressplus/goods/table77.jpg", "detectData": [{"object_confidence": 98, "object_name": "\u684c\u5b50", "object_bounding_box": {"y": 0.5381471389645777, "width": 0.46090909090909093, "height": 0.44141689373297005, "x": 0.3718181818181818}}]}, "table74": {"fileUrl": "http://ot2gqnlv6.bkt.clouddn.com/dressplus/goods/table74.jpg", "detectData": []}, "table75": {"fileUrl": "http://ot2gqnlv6.bkt.clouddn.com/dressplus/goods/table75.jpg", "detectData": [{"object_confidence": 86, "object_name": "\u684c\u5b50", "object_bounding_box": {"y": 0.5607094133697135, "width": 0.38636363636363635, "height": 0.37517053206002726, "x": 0.3809090909090909}}]}, "table72": {"fileUrl": "http://ot2gqnlv6.bkt.clouddn.com/dressplus/goods/table72.jpg", "detectData": []}, "table73": {"fileUrl": "http://ot2gqnlv6.bkt.clouddn.com/dressplus/goods/table73.jpg", "detectData": []}, "table70": {"fileUrl": "http://ot2gqnlv6.bkt.clouddn.com/dressplus/goods/table70.jpg", "detectData": [{"object_confidence": 76, "object_name": "\u684c\u5b50", "object_bounding_box": {"y": 0.5095628415300546, "width": 0.44181818181818183, "height": 0.4713114754098361, "x": 0.4090909090909091}}]}, "table71": {"fileUrl": "http://ot2gqnlv6.bkt.clouddn.com/dressplus/goods/table71.jpg", "detectData": []}}